x_spaces_dl-1.0.8.dist-info/licenses/LICENSE
xspacedl/__init__.py
xspacedl/__main__.py
xspacedl/auth.py
xspacedl/cli.py
xspacedl/config.py
xspacedl/core.py
xspacedl/downloader.py
xspacedl/exceptions.py
xspacedl/metadata.py
xspacedl/utils.py
xspacesdl/__init__.py
xspacesdl/__main__.py
xspacesdl/auth.py
xspacesdl/cli.py
xspacesdl/config.py
xspacesdl/core.py
xspacesdl/downloader.py
xspacesdl/exceptions.py
xspacesdl/metadata.py
xspacesdl/utils.py
x_spaces_dl-1.0.8.dist-info/METADATA
x_spaces_dl-1.0.8.dist-info/WHEEL
x_spaces_dl-1.0.8.dist-info/entry_points.txt
x_spaces_dl-1.0.8.dist-info/top_level.txt
x_spaces_dl-1.0.8.dist-info/RECORD
