Metadata-Version: 2.4
Name: x-spaces-dl
Version: 1.0.8
Summary: A powerful command-line tool and Python library for downloading Twitter/X Spaces recordings
Home-page: https://github.com/w3Abhishek/x-spaces-dl
Author: pyvrma
Author-email: pyvrma <insightfulverma@gmail.com>
License: MIT
Project-URL: Homepage, https://github.com/w3Abhishek/x-spaces-dl
Project-URL: Documentation, https://github.com/w3Abhishek/x-spaces-dl#readme
Project-URL: Repository, https://github.com/w3Abhishek/x-spaces-dl
Project-URL: Issues, https://github.com/w3Abhishek/x-spaces-dl/issues
Keywords: twitter,x,spaces,download,audio,recording,cli
Classifier: Development Status :: 4 - Beta
Classifier: Intended Audience :: Developers
Classifier: Intended Audience :: End Users/Desktop
Classifier: License :: OSI Approved :: MIT License
Classifier: Operating System :: OS Independent
Classifier: Programming Language :: Python :: 3
Classifier: Programming Language :: Python :: 3.10
Classifier: Programming Language :: Python :: 3.11
Classifier: Programming Language :: Python :: 3.12
Classifier: Programming Language :: Python :: 3.13
Classifier: Topic :: Internet :: WWW/HTTP
Classifier: Topic :: Multimedia :: Sound/Audio :: Capture/Recording
Classifier: Topic :: Software Development :: Libraries :: Python Modules
Requires-Python: >=3.10
License-File: LICENSE
Requires-Dist: click>=8.3.0
Requires-Dist: mutagen>=1.47.0
Requires-Dist: python-dateutil>=2.9.0.post0
Requires-Dist: pyyaml>=6.0.3
Requires-Dist: requests>=2.32.5
Requires-Dist: rich>=14.2.0
Requires-Dist: tqdm>=4.67.1
Provides-Extra: dev
Requires-Dist: black>=25.9.0; extra == "dev"
Requires-Dist: flake8>=7.3.0; extra == "dev"
Requires-Dist: isort>=7.0.0; extra == "dev"
Requires-Dist: mypy>=1.18.2; extra == "dev"
Requires-Dist: pytest>=8.4.2; extra == "dev"
Requires-Dist: pytest-cov>=7.0.0; extra == "dev"
Dynamic: author
Dynamic: home-page
Dynamic: license-file
Dynamic: requires-python
